enquire/__init__.py
enquire/prompt.py
enquire/style.py
enquire/question/__init__.py
enquire/question/base.py
enquire/question/boolean.py
enquire/question/checkbox.py
enquire/question/radio.py
enquire/question/text.py
enquire/question/wrappable.py
enquire/validation/__init__.py
enquire-0.1.0.dist-info/METADATA
enquire-0.1.0.dist-info/WHEEL
enquire-0.1.0.dist-info/top_level.txt
enquire-0.1.0.dist-info/RECORD
