Metadata-Version: 2.1
Name: enquire
Version: 0.1.0
Summary: PyInquirer-inspired prompt library
Author-email: Pavel Vorobyev <viert.ru@gmail.com>
License: MIT
Project-URL: repository, https://github.com/viert/enquire
Keywords: click,PyInquirer,prompt-toolkit,cli,command-line,commandline,command-line-interface,python-inquiry,inquirer
Classifier: Programming Language :: Python :: 3
Requires-Python: >=3.10
Requires-Dist: prompt-toolkit
